torrent_downloader/__init__.py
torrent_downloader/server.py
torrent_downloader/static/index.html
torrent_downloader/static/vite.svg
torrent_downloader/static/assets/index-1tlJV8lw.css
torrent_downloader/static/assets/index-DNc3M5gl.js
torrent_downloader_react-1.2.0.dist-info/METADATA
torrent_downloader_react-1.2.0.dist-info/WHEEL
torrent_downloader_react-1.2.0.dist-info/entry_points.txt
torrent_downloader_react-1.2.0.dist-info/top_level.txt
torrent_downloader_react-1.2.0.dist-info/RECORD
