Metadata-Version: 2.1
Name: torrent-downloader-react
Version: 1.2.0
Summary: A high-performance, React-based BitTorrent client with an intuitive interface for seamless file downloading
Home-page: https://github.com/stevenyyan/torrent-downloader
Author: Steven Yan
Author-email: yulong.yan@uqconnect.edu.au
Project-URL: Bug Tracker, https://github.com/stevenyyan/torrent-downloader/issues
Project-URL: Documentation, https://github.com/stevenyyan/torrent-downloader#readme
Project-URL: Source Code, https://github.com/stevenyyan/torrent-downloader
Keywords: torrent,downloader,p2p,bittorrent,libtorrent
Classifier: Development Status :: 4 - Beta
Classifier: Environment :: Web Environment
Classifier: Framework :: FastAPI
Classifier: Intended Audience :: End Users/Desktop
Classifier: License :: OSI Approved :: MIT License
Classifier: Operating System :: OS Independent
Classifier: Programming Language :: Python :: 3
Classifier: Programming Language :: Python :: 3.8
Classifier: Programming Language :: Python :: 3.9
Classifier: Programming Language :: Python :: 3.10
Classifier: Programming Language :: Python :: 3.11
Classifier: Topic :: Internet :: WWW/HTTP
Classifier: Topic :: Internet :: WWW/HTTP :: HTTP Servers
Requires-Python: >=3.8
Requires-Dist: fastapi>=0.109.0
Requires-Dist: uvicorn>=0.27.0
Requires-Dist: pydantic>=2.0.0
Requires-Dist: libtorrent>=2.0.0
Requires-Dist: pytest>=8.0.0
Requires-Dist: httpx>=0.27.0
